{"error":false,"message":"200 OK","categories":[{"id":1,"name":"UI/UX Design","createdAt":"2023-12-15T14:08:30.423Z","updatedAt":"2023-12-15T14:08:30.423Z","imageUrl":"https://ik.imagekit.io/qgv8ukjrn/CourseImage/Ui-ux-cover-imge_rJZxLF3Lr.jpg"},{"id":2,"name":"Web Development","createdAt":"2023-12-16T13:19:29.463Z","updatedAt":"2023-12-16T13:19:29.463Z","imageUrl":"https://ik.imagekit.io/qgv8ukjrn/CourseImage/Python-Data-Science-Tutorial_vum0TtE9y.jpg"},{"id":3,"name":"Data Science","createdAt":"2023-12-16T13:25:09.783Z","updatedAt":"2023-12-16T13:25:09.783Z","imageUrl":""},{"id":4,"name":"Business Intelligence","createdAt":"2023-12-16T13:25:43.872Z","updatedAt":"2023-12-16T13:25:43.872Z","imageUrl":""},{"id":5,"name":"Android Development","createdAt":"2023-12-16T13:26:06.920Z","updatedAt":"2023-12-16T13:26:06.920Z","imageUrl":""},{"id":6,"name":"Product Management","createdAt":"2023-12-16T15:12:14.398Z","updatedAt":"2023-12-16T15:12:14.398Z","imageUrl":""},{"id":7,"name":"iOS Development","createdAt":"2023-12-16T15:12:40.990Z","updatedAt":"2023-12-16T15:12:40.990Z","imageUrl":""}]}